openfacekit/__init__.py
openfacekit/face_recognition.py
openfacekit/utils.py
openfacekit-0.2.0.dist-info/licenses/LICENSE
openfacekit-0.2.0.dist-info/METADATA
openfacekit-0.2.0.dist-info/WHEEL
openfacekit-0.2.0.dist-info/top_level.txt
openfacekit-0.2.0.dist-info/RECORD
